impala/__init__.py
impala/_thrift_api.py
impala/_version.py
impala/compat.py
impala/dbapi.py
impala/error.py
impala/hiveserver2.py
impala/interface.py
impala/sasl_compat.py
impala/sqlalchemy.py
impala/util.py
impala/_thrift_gen/__init__.py
impala/_thrift_gen/ErrorCodes/__init__.py
impala/_thrift_gen/ErrorCodes/constants.py
impala/_thrift_gen/ErrorCodes/ttypes.py
impala/_thrift_gen/ExecStats/__init__.py
impala/_thrift_gen/ExecStats/constants.py
impala/_thrift_gen/ExecStats/ttypes.py
impala/_thrift_gen/ImpalaService/ImpalaHiveServer2Service.py
impala/_thrift_gen/ImpalaService/ImpalaService.py
impala/_thrift_gen/ImpalaService/__init__.py
impala/_thrift_gen/ImpalaService/constants.py
impala/_thrift_gen/ImpalaService/ttypes.py
impala/_thrift_gen/Metrics/__init__.py
impala/_thrift_gen/Metrics/constants.py
impala/_thrift_gen/Metrics/ttypes.py
impala/_thrift_gen/RuntimeProfile/__init__.py
impala/_thrift_gen/RuntimeProfile/constants.py
impala/_thrift_gen/RuntimeProfile/ttypes.py
impala/_thrift_gen/Status/__init__.py
impala/_thrift_gen/Status/constants.py
impala/_thrift_gen/Status/ttypes.py
impala/_thrift_gen/TCLIService/TCLIService.py
impala/_thrift_gen/TCLIService/__init__.py
impala/_thrift_gen/TCLIService/constants.py
impala/_thrift_gen/TCLIService/ttypes.py
impala/_thrift_gen/Types/__init__.py
impala/_thrift_gen/Types/constants.py
impala/_thrift_gen/Types/ttypes.py
impala/_thrift_gen/beeswax/BeeswaxService.py
impala/_thrift_gen/beeswax/__init__.py
impala/_thrift_gen/beeswax/constants.py
impala/_thrift_gen/beeswax/ttypes.py
impala/_thrift_gen/fb303/FacebookService.py
impala/_thrift_gen/fb303/__init__.py
impala/_thrift_gen/fb303/constants.py
impala/_thrift_gen/fb303/ttypes.py
impala/_thrift_gen/hive_metastore/ThriftHiveMetastore.py
impala/_thrift_gen/hive_metastore/__init__.py
impala/_thrift_gen/hive_metastore/constants.py
impala/_thrift_gen/hive_metastore/ttypes.py
impala/tests/__init__.py
impala/tests/_dbapi20_tests.py
impala/tests/compat.py
impala/tests/conftest.py
impyla_jz-0.16.3.dist-info/LICENSE.txt
impyla_jz-0.16.3.dist-info/METADATA
impyla_jz-0.16.3.dist-info/WHEEL
impyla_jz-0.16.3.dist-info/entry_points.txt
impyla_jz-0.16.3.dist-info/top_level.txt
impyla_jz-0.16.3.dist-info/RECORD
