Metadata-Version: 2.1
Name: impyla-jz
Version: 0.16.3
Summary: Python client for the Impala distributed query engine
Home-page: https://github.com/Guanpx/superset/tree/0.36.0
Author: pxguan
Author-email: guanpeixiang@foxmail.com
Maintainer: Wes McKinney
Maintainer-email: wes.mckinney@twosigma.com
License: Apache License, Version 2.0
Keywords: cloudera impala python hadoop sql hdfs mpp spark pydata pandas distributed db api pep 249 hive hiveserver2 hs2
Platform: UNKNOWN
Classifier: Programming Language :: Python :: 3
Classifier: Programming Language :: Python :: 3.4
Classifier: Programming Language :: Python :: 3.5
Classifier: Programming Language :: Python :: 3.6
Classifier: Programming Language :: Python :: 3.7
Classifier: Programming Language :: Python :: 3.8
Classifier: Programming Language :: Python :: 3.9
Requires-Dist: six
Requires-Dist: bitarray
Requires-Dist: thrift (==0.9.3) ; python_version<'3.0'
Requires-Dist: thriftpy2 (<0.5.0,>=0.4.0) ; python_version>='3.0'
Provides-Extra: kerberos
Requires-Dist: thrift-sasl (==0.2.1) ; extra == 'kerberos'
